elog/__init__.py
elog/elog.py
elog_thiago1080-0.0.5.dist-info/METADATA
elog_thiago1080-0.0.5.dist-info/WHEEL
elog_thiago1080-0.0.5.dist-info/licenses/LICENSE
elog_thiago1080-0.0.5.dist-info/RECORD
