Metadata-Version: 2.1
Name: elog_thiago1080
Version: 0.0.5
Summary: This is a Python package that provides decorators for logging function execution and timing function execution.
Project-URL: Homepage, https://github.com/thiago1080/log_exc_decorator
Project-URL: Bug Tracker, https://github.com/thiago1080/log_exc_decorator/issues
Author-email: Thiago Henrique Martinelli <thiago.henrique.martinelli@gmail.com>
License-File: LICENSE
Classifier: License :: OSI Approved :: Apache Software License
Classifier: Operating System :: OS Independent
Classifier: Programming Language :: Python :: 3
Requires-Python: >=3.7
Requires-Dist: loguru>=0.5.3
